heliopy/__init__.py
heliopy/_version.py
heliopy/heliopyrc
heliopy/data/__init__.py
heliopy/data/ace.py
heliopy/data/artemis.py
heliopy/data/cassini.py
heliopy/data/cdasrest.py
heliopy/data/cluster.py
heliopy/data/dscovr.py
heliopy/data/helios.py
heliopy/data/helper.py
heliopy/data/imp.py
heliopy/data/messenger.py
heliopy/data/mms.py
heliopy/data/omni.py
heliopy/data/psp.py
heliopy/data/solo.py
heliopy/data/spice.py
heliopy/data/stereo.py
heliopy/data/sunspot.py
heliopy/data/ulysses.py
heliopy/data/util.py
heliopy/data/voyager.py
heliopy/data/wind.py
heliopy/models/__init__.py
heliopy/models/test/__init__.py
heliopy/models/test/test_models.py
heliopy/spice/__init__.py
heliopy/spice/spice.py
heliopy/util/__init__.py
heliopy/util/config.py
HelioPy-1.0.0.dist-info/LICENSE
HelioPy-1.0.0.dist-info/METADATA
HelioPy-1.0.0.dist-info/WHEEL
HelioPy-1.0.0.dist-info/top_level.txt
HelioPy-1.0.0.dist-info/RECORD
